tests/__init__.py
tests/cipher_suite_tester.py
tests/conftest.py
tests/openssl_command.py
tlsmate/__init__.py
tlsmate/_version.py
tlsmate/cert.py
tlsmate/cert_chain.py
tlsmate/cert_utils.py
tlsmate/client.py
tlsmate/client_auth.py
tlsmate/client_state.py
tlsmate/command.py
tlsmate/config.py
tlsmate/connection.py
tlsmate/crl_manager.py
tlsmate/dh_numbers.py
tlsmate/ext.py
tlsmate/kdf.py
tlsmate/key_exchange.py
tlsmate/key_logging.py
tlsmate/mappings.py
tlsmate/msg.py
tlsmate/pdu.py
tlsmate/plugin.py
tlsmate/record_layer.py
tlsmate/record_layer_state.py
tlsmate/recorder.py
tlsmate/resolver.py
tlsmate/server_profile.py
tlsmate/socket.py
tlsmate/structs.py
tlsmate/tls.py
tlsmate/tlsmate.py
tlsmate/tlssuite.py
tlsmate/trust_store.py
tlsmate/utils.py
tlsmate/version.py
tlsmate/plugins/__init__.py
tlsmate/plugins/scan.py
tlsmate/plugins/version.py
tlsmate/styles/default.yaml
tlsmate/workers/__init__.py
tlsmate/workers/base_vulnerabilities.py
tlsmate/workers/ccs_injection.py
tlsmate/workers/compression.py
tlsmate/workers/dh_params.py
tlsmate/workers/downgrade.py
tlsmate/workers/encrypt_then_mac.py
tlsmate/workers/ephemeral_key_reuse.py
tlsmate/workers/eval_cipher_suites.py
tlsmate/workers/grease.py
tlsmate/workers/heartbeat.py
tlsmate/workers/heartbleed.py
tlsmate/workers/master_secret.py
tlsmate/workers/ocsp_stapling.py
tlsmate/workers/padding_oracle.py
tlsmate/workers/renegotiation.py
tlsmate/workers/resumption.py
tlsmate/workers/robot.py
tlsmate/workers/scanner_info.py
tlsmate/workers/server_profile.py
tlsmate/workers/sig_algo.py
tlsmate/workers/supported_groups.py
tlsmate/workers/text_server_profile.py
tlsmate-1.2.2.dist-info/LICENSE
tlsmate-1.2.2.dist-info/METADATA
tlsmate-1.2.2.dist-info/WHEEL
tlsmate-1.2.2.dist-info/entry_points.txt
tlsmate-1.2.2.dist-info/top_level.txt
tlsmate-1.2.2.dist-info/zip-safe
tlsmate-1.2.2.dist-info/RECORD
