Metadata-Version: 2.1
Name: tlsmate
Version: 1.2.2
Summary: Simulate a TLS client and scan a TLS server
Home-page: https://gitlab.com/guballa/tlsmate
Author: Jens Guballa
Author-email: jens@guballa.de
License: MIT
Project-URL: Bug Tracker, https://gitlab.com/guballa/tlsmate/issues
Project-URL: Changelog, https://gitlab.com/guballa/tlsmate/-/blob/master/CHANGELOG.rst
Project-URL: Source, https://gitlab.com/guballa/tlsmate
Keywords: tls client simulator scan scanner server
Platform: any
Classifier: Development Status :: 3 - Alpha
Classifier: Intended Audience :: Developers
Classifier: License :: OSI Approved :: MIT License
Classifier: Operating System :: OS Independent
Classifier: Programming Language :: Python
Classifier: Programming Language :: Python :: 3.6
Classifier: Programming Language :: Python :: 3.7
Classifier: Programming Language :: Python :: 3.8
Classifier: Topic :: Software Development :: Libraries :: Python Modules
Requires-Python: <4,>=3.6
License-File: LICENSE
Requires-Dist: cryptography (>=36)
Requires-Dist: pyyaml
Requires-Dist: pem
Requires-Dist: configparser
Requires-Dist: marshmallow
Requires-Dist: marshmallow-oneofschema
Requires-Dist: colorama
Requires-Dist: requests
Requires-Dist: pysocks
Requires-Dist: dnspython[doh]
Requires-Dist: dataclasses ; python_version < "3.7"
Requires-Dist: importlib-metadata ; python_version < "3.8"
Provides-Extra: dev
Requires-Dist: wheel ; extra == 'dev'
Requires-Dist: pytest ; extra == 'dev'
Requires-Dist: pytest-cov ; extra == 'dev'
Requires-Dist: black (==19.10b0) ; extra == 'dev'
Requires-Dist: flake8 ; extra == 'dev'
Requires-Dist: sphinx ; extra == 'dev'
Requires-Dist: sphinx-argparse ; extra == 'dev'
Requires-Dist: tox ; extra == 'dev'
Requires-Dist: sphinx-rtd-theme ; extra == 'dev'
Requires-Dist: mypy ; extra == 'dev'
Requires-Dist: types-requests ; extra == 'dev'
Requires-Dist: types-PyYAML ; extra == 'dev'
